uvulog/__init__.py
uvulog/core.py
uvulog-1.0.4.dist-info/licenses/LICENSE
uvulog-1.0.4.dist-info/METADATA
uvulog-1.0.4.dist-info/WHEEL
uvulog-1.0.4.dist-info/top_level.txt
uvulog-1.0.4.dist-info/RECORD
