Metadata-Version: 2.4
Name: uvulog
Version: 1.0.4
Summary: A simple logger for console and file logging, with colored output and log rotation.
Home-page: https://github.com/lupnis/uvulog
Author: Lupnis J H
Author-email: Lupnis J H <lupnisj@gmail.com>
License: MIT
Keywords: logger,logging,console,file,colored,log rotation
Requires-Python: >=3.8.0
License-File: LICENSE
Requires-Dist: filelock
Dynamic: author
Dynamic: home-page
Dynamic: license-file
Dynamic: requires-python
